atlalign/__init__.py
atlalign/augmentations.py
atlalign/base.py
atlalign/data.py
atlalign/metrics.py
atlalign/nn.py
atlalign/utils.py
atlalign/visualization.py
atlalign/volume.py
atlalign/zoo.py
atlalign/label/__init__.py
atlalign/label/cli.py
atlalign/label/io.py
atlalign/label/new_GUI.py
atlalign/ml_utils/__init__.py
atlalign/ml_utils/augmentation.py
atlalign/ml_utils/callbacks.py
atlalign/ml_utils/io.py
atlalign/ml_utils/layers.py
atlalign/ml_utils/losses.py
atlalign/ml_utils/models.py
atlalign/non_ml/__init__.py
atlalign/non_ml/intensity.py
atlalign-0.6.2.dist-info/AUTHORS.md
atlalign-0.6.2.dist-info/LICENSE.md
atlalign-0.6.2.dist-info/METADATA
atlalign-0.6.2.dist-info/WHEEL
atlalign-0.6.2.dist-info/entry_points.txt
atlalign-0.6.2.dist-info/top_level.txt
atlalign-0.6.2.dist-info/RECORD
