Metadata-Version: 2.1
Name: atlalign
Version: 0.6.2
Summary: Blue Brain multi-modal registration and alignment toolbox
Home-page: https://github.com/BlueBrain/atlas_alignment
Author: Blue Brain Project, EPFL
License: LGPLv3
Classifier: Development Status :: 4 - Beta
Classifier: License :: OSI Approved :: GNU Lesser General Public License v3 (LGPLv3)
Classifier: Operating System :: Unix
Classifier: Programming Language :: Python
Classifier: Programming Language :: Python :: 3
Classifier: Programming Language :: Python :: 3.6
Classifier: Programming Language :: Python :: 3.7
Classifier: Programming Language :: Python :: 3.8
Classifier: Programming Language :: Python :: 3.9
Classifier: Programming Language :: Python :: 3 :: Only
Classifier: Topic :: Scientific/Engineering :: Artificial Intelligence
Classifier: Topic :: Scientific/Engineering :: Image Processing
Classifier: Topic :: Software Development :: Libraries :: Python Modules
Requires-Python: >=3.6.0
License-File: LICENSE.md
License-File: AUTHORS.md
Requires-Dist: antspyx
Requires-Dist: imgaug <0.3
Requires-Dist: matplotlib >=3.0.3
Requires-Dist: mlflow
Requires-Dist: nibabel >=2.4.0
Requires-Dist: numpy <1.24.0
Requires-Dist: seaborn
Requires-Dist: scikit-image >=0.17.1
Requires-Dist: scikit-learn >=0.20.2
Requires-Dist: scipy
Requires-Dist: tensorflow >=2.6.0
Requires-Dist: tensorflow-addons
Provides-Extra: dev
Requires-Dist: black >=20.8b1 ; extra == 'dev'
Requires-Dist: flake8 >=3.7.4 ; extra == 'dev'
Requires-Dist: pydocstyle >=3.0.0 ; extra == 'dev'
Requires-Dist: pytest >=3.10.1 ; extra == 'dev'
Requires-Dist: pytest-cov ; extra == 'dev'
Requires-Dist: pytest-mock >=1.10.1 ; extra == 'dev'
Provides-Extra: docs
Requires-Dist: sphinx >=1.3 ; extra == 'docs'
Requires-Dist: sphinx-bluebrain-theme ; extra == 'docs'
